[{"name":"trading_site","value":"site1.sbisec.co.jp","domain":".sbisec.co.jp","path":"/ETGate","expires":-1,"size":30,"httpOnly":false,"secure":false,"session":true,"priority":"Medium","sameParty":false,"sourceScheme":"Secure","sourcePort":443},{"name":"visitor_filter","value":"site1.sbisec.co.jp","domain":".sbisec.co.jp","path":"/ETGate","expires":1790059038.54205,"size":32,"httpOnly":false,"secure":false,"session":false,"priority":"Medium","sameParty":false,"sourceScheme":"Secure","sourcePort":443},{"name":"JSESSIONID","value":"33A499725B99D897E1298D5991E26D76.tom11","domain":"chart.iris.sbisec.co.jp","path":"/sbi","expires":-1,"size":48,"httpOnly":true,"secure":false,"session":true,"priority":"Medium","sameParty":false,"sourceScheme":"Secure","sourcePort":443},{"name":"krt.vis","value":"m_lJGXR1DgMaAUq","domain":".sbisec.co.jp","path":"/","expires":1790059038.587092,"size":22,"httpOnly":false,"secure":true,"session":false,"priority":"Medium","sameParty":false,"sourceScheme":"Secure","sourcePort":443},{"name":"s_fid","value":"41A0FFBF99AA7D40-39988CD82427935B","domain":".sbisec.co.jp","path":"/","expires":1790059038.721356,"size":38,"httpOnly":false,"secure":false,"session":false,"priority":"Medium","sameParty":false,"sourceScheme":"Secure","sourcePort":443},{"name":"sc_vid","value":"175549649293024593609857808940","domain":".sbisec.co.jp","path":"/","expires":1790056492.930462,"size":36,"httpOnly":false,"secure":false,"session":false,"priority":"Medium","sameParty":false,"sourceScheme":"Secure","sourcePort":443},{"name":"s_cc","value":"true","domain":".sbisec.co.jp","path":"/","expires":-1,"size":8,"httpOnly":false,"secure":false,"session":true,"priority":"Medium","sameParty":false,"sourceScheme":"Secure","sourcePort":443},{"name":"rt_storage_writable","value":"true","domain":".sbisec.co.jp","path":"/","expires":1755585438,"size":23,"httpOnly":false,"secure":true,"session":false,"priority":"Medium","sameParty":false,"sourceScheme":"Secure","sourcePort":443},{"name":"rt_session_id","value":"3b907a024caf45c78b40089858ae63b2","domain":".sbisec.co.jp","path":"/","expires":1755500848,"size":45,"httpOnly":false,"secure":true,"session":false,"priority":"Medium","sameParty":false,"sourceScheme":"Secure","sourcePort":443},{"name":"rt_user_id","value":"e91ca516133f45d49446e371a911d0aa","domain":".sbisec.co.jp","path":"/","expires":1790059039.98155,"size":42,"httpOnly":false,"secure":true,"session":false,"priority":"Medium","sameParty":false,"sourceScheme":"Secure","sourcePort":443},{"name":"robee_uid","value":"d9d801f0871fd7ae3b9907164e102af31755496493036","domain":".sbisec.co.jp","path":"/","expires":1790059037.415582,"size":54,"httpOnly":false,"secure":false,"session":false,"priority":"Medium","sameParty":false,"sourceScheme":"Secure","sourcePort":443},{"name":"_pk_ses.1501274415.3f90","value":"*","domain":"www.sbisec.co.jp","path":"/","expires":1755500836,"size":24,"httpOnly":false,"secure":false,"session":false,"priority":"Medium","sameParty":false,"sourceScheme":"Secure","sourcePort":443},{"name":"ct1","value":"kwndM80572j97P0N4r8GE","domain":".sbisec.co.jp","path":"/","expires":1787035037,"size":24,"httpOnly":false,"secure":true,"session":false,"priority":"Medium","sameParty":false,"sourceScheme":"Secure","sourcePort":443},{"name":"_imdb_matag_localid","value":"62125e78-3b8b-4fc3-b918-9b3485e0ab1d","domain":".sbisec.co.jp","path":"/","expires":1787035037,"size":55,"httpOnly":false,"secure":false,"session":false,"sameSite":"Lax","priority":"Medium","sameParty":false,"sourceScheme":"Secure","sourcePort":443},{"name":"_im_vid","value":"01K2XVXCFKADW0TV42ZDKTBRTH","domain":".www.sbisec.co.jp","path":"/","expires":1790059037,"size":33,"httpOnly":false,"secure":false,"session":false,"sameSite":"Lax","priority":"Medium","sameParty":false,"sourceScheme":"Secure","sourcePort":443},{"name":"__gunoad","value":"3af139f9-027e-461e-954f-03afd0f898f6","domain":"www.sbisec.co.jp","path":"/","expires":1790056493.572639,"size":44,"httpOnly":false,"secure":false,"session":false,"priority":"Medium","sameParty":false,"sourceScheme":"Secure","sourcePort":443},{"name":"_im_uid.11283","value":"h.0619578be47c9c05","domain":".www.sbisec.co.jp","path":"/","expires":1763275037,"size":31,"httpOnly":false,"secure":true,"session":false,"sameSite":"None","priority":"Medium","sameParty":false,"sourceScheme":"Secure","sourcePort":443},{"name":"receive-cookie-deprecation","value":"1","domain":".im-apps.net","path":"/","expires":1771051038.951499,"size":27,"httpOnly":true,"secure":true,"session":false,"sameSite":"None","priority":"Medium","sameParty":false,"sourceScheme":"Secure","sourcePort":443,"partitionKey":{"sourceOrigin":"https://sbisec.co.jp","hasCrossSiteAncestor":true}},{"name":"_gcl_au","value":"1.1.1777060133.1755497381","domain":".sbisec.co.jp","path":"/","expires":1763273380,"size":32,"httpOnly":false,"secure":false,"session":false,"priority":"Medium","sameParty":false,"sourceScheme":"Secure","sourcePort":443},{"name":"_yjsu_yjad","value":"1755497380.dfd02732-bcb4-48e9-87f0-f8fc9f0ef4e3","domain":".sbisec.co.jp","path":"/","expires":1787033380,"size":57,"httpOnly":false,"secure":false,"session":false,"priority":"Medium","sameParty":false,"sourceScheme":"Secure","sourcePort":443},{"name":"_fbp","value":"fb.2.1755497380808.37388480714570476","domain":".sbisec.co.jp","path":"/","expires":1763275039,"size":40,"httpOnly":false,"secure":false,"session":false,"sameSite":"Lax","priority":"Medium","sameParty":false,"sourceScheme":"Secure","sourcePort":443},{"name":"__lt__cid","value":"85e93937-f4e1-42d4-abf4-3fa80c181a3e","domain":".site1.sbisec.co.jp","path":"/","expires":1790059039.071636,"size":45,"httpOnly":false,"secure":false,"session":false,"priority":"Medium","sameParty":false,"sourceScheme":"Secure","sourcePort":443},{"name":"__lt__sid","value":"46c88155-5574efed","domain":".site1.sbisec.co.jp","path":"/","expires":1755500839,"size":26,"httpOnly":false,"secure":false,"session":false,"priority":"Medium","sameParty":false,"sourceScheme":"Secure","sourcePort":443},{"name":"__pp_uid","value":"xZ6AxsiTqXVUnmJsHJvPMCqFagGnMfE2","domain":".sbisec.co.jp","path":"/","expires":1790059039.349256,"size":40,"httpOnly":false,"secure":false,"session":false,"priority":"Medium","sameParty":false,"sourceScheme":"Secure","sourcePort":443},{"name":"_unv_aid","value":"4ba4b4db-5ffb-46e6-90eb-cc0e0bbbaa43","domain":".sbisec.co.jp","path":"/","expires":1763275039.321837,"size":44,"httpOnly":false,"secure":false,"session":false,"priority":"Medium","sameParty":false,"sourceScheme":"Secure","sourcePort":443},{"name":"_im_vid","value":"01K2XWRF18K51NQNM4BYP88TD3","domain":".site1.sbisec.co.jp","path":"/","expires":1790059068,"size":33,"httpOnly":false,"secure":false,"session":false,"sameSite":"Lax","priority":"Medium","sameParty":false,"sourceScheme":"Secure","sourcePort":443},{"name":"_unv_id","value":"_unv_id","domain":".sbisec.co.jp","path":"/","expires":1755500981.055821,"size":14,"httpOnly":false,"secure":false,"session":false,"priority":"Medium","sameParty":false,"sourceScheme":"Secure","sourcePort":443},{"name":"_tt_enable_cookie","value":"1","domain":".sbisec.co.jp","path":"/","expires":1789195039,"size":18,"httpOnly":false,"secure":false,"session":false,"priority":"Medium","sameParty":false,"sourceScheme":"Secure","sourcePort":443},{"name":"_ttp","value":"01K2XWRF78BT87RZ4C69Q8T7Y0_.tt.2","domain":".sbisec.co.jp","path":"/","expires":1789195039,"size":36,"httpOnly":false,"secure":false,"session":false,"priority":"Medium","sameParty":false,"sourceScheme":"Secure","sourcePort":443},{"name":"_im_id.1018313","value":"8d7ef4cdf38a85f3.1755497381.","domain":"site1.sbisec.co.jp","path":"/","expires":1789452581,"size":42,"httpOnly":false,"secure":false,"session":false,"sameSite":"Lax","priority":"Medium","sameParty":false,"sourceScheme":"Secure","sourcePort":443},{"name":"_im_ses.1018313","value":"1","domain":"site1.sbisec.co.jp","path":"/","expires":1755500839,"size":16,"httpOnly":false,"secure":false,"session":false,"sameSite":"Lax","priority":"Medium","sameParty":false,"sourceScheme":"Secure","sourcePort":443},{"name":"_ga","value":"GA1.1.647591098.1755497382","domain":".sbisec.co.jp","path":"/","expires":1790057381.735952,"size":29,"httpOnly":false,"secure":false,"session":false,"priority":"Medium","sameParty":false,"sourceScheme":"Secure","sourcePort":443},{"name":"XANDR_PANID","value":"xFly4Q9n859C8N3c8m80mQf3rioPn59aJ7-vHNJyUmVd8urVCw19c8BECOgdc2pSdJ8SSsrQHf3qeqlWRq89LVHVCu9JREIAZpMA-Q7Bd9U.","domain":".adnxs.com","path":"/","expires":1763275040.088419,"size":119,"httpOnly":false,"secure":true,"session":false,"sameSite":"None","priority":"Medium","sameParty":false,"sourceScheme":"Secure","sourcePort":443,"partitionKey":{"sourceOrigin":"https://sbisec.co.jp","hasCrossSiteAncestor":true}},{"name":"t_pt_gid","value":"ffdbe8cc-642b-4731-962a-b287b3a55f21-tuctf9c4926","domain":".taboola.com","path":"/","expires":1787035040.061725,"size":56,"httpOnly":false,"secure":true,"session":false,"sameSite":"None","priority":"Medium","sameParty":false,"sourceScheme":"Secure","sourcePort":443,"partitionKey":{"sourceOrigin":"https://sbisec.co.jp","hasCrossSiteAncestor":true}},{"name":"_cq_duid","value":"1.1755497382.ZyGMFssLm88Vidxi","domain":".sbisec.co.jp","path":"/","expires":1763383040,"size":37,"httpOnly":false,"secure":true,"session":false,"sameSite":"None","priority":"Medium","sameParty":false,"sourceScheme":"Secure","sourcePort":443},{"name":"_cq_suid","value":"1.1755497382.g1chXifWZRGdB7fu","domain":".sbisec.co.jp","path":"/","expires":-1,"size":37,"httpOnly":false,"secure":true,"session":true,"sameSite":"None","priority":"Medium","sameParty":false,"sourceScheme":"Secure","sourcePort":443},{"name":"tluidp","value":"3621449740798420019541","domain":".3lift.com","path":"/","expires":1763275040.361721,"size":28,"httpOnly":false,"secure":true,"session":false,"sameSite":"None","priority":"Medium","sameParty":false,"sourceScheme":"Secure","sourcePort":443,"partitionKey":{"sourceOrigin":"https://sbisec.co.jp","hasCrossSiteAncestor":true}},{"name":"khaos_p","value":"MEGPTD8F-D-1FIR","domain":".rubiconproject.com","path":"/","expires":1787035040.154955,"size":22,"httpOnly":false,"secure":true,"session":false,"sameSite":"None","priority":"Medium","sameParty":false,"sourceScheme":"Secure","sourcePort":443,"partitionKey":{"sourceOrigin":"https://sbisec.co.jp","hasCrossSiteAncestor":true}},{"name":"receive-cookie-deprecation","value":"1","domain":".rubiconproject.com","path":"/","expires":1763275040.154986,"size":27,"httpOnly":true,"secure":true,"session":false,"sameSite":"None","priority":"Medium","sameParty":false,"sourceScheme":"Secure","sourcePort":443,"partitionKey":{"sourceOrigin":"https://sbisec.co.jp","hasCrossSiteAncestor":true}},{"name":"_clck","value":"d6htm0%7C2%7Cfyk%7C0%7C2056","domain":".sbisec.co.jp","path":"/","expires":1787033382,"size":32,"httpOnly":false,"secure":false,"session":false,"priority":"Medium","sameParty":false,"sourceScheme":"Secure","sourcePort":443},{"name":"_pk_id.1501274415.3f90","value":"309d7cd5f7053818.1755496493.1.1755499037.1755496493.","domain":"www.sbisec.co.jp","path":"/","expires":1789451693,"size":74,"httpOnly":false,"secure":false,"session":false,"priority":"Medium","sameParty":false,"sourceScheme":"Secure","sourcePort":443},{"name":"robee_sid","value":"6c291755499037007","domain":".sbisec.co.jp","path":"/","expires":1755499217,"size":26,"httpOnly":false,"secure":false,"session":false,"priority":"Medium","sameParty":false,"sourceScheme":"Secure","sourcePort":443},{"name":"AWSALB","value":"DaC9ufoOOSYsszGVO/bA2F2sDPqqzFczEYVkCipe1H6Skk/7DkXwZX3AZ5/Z5NhuwYHYwPMT59xBIRvMrfLPQobCYT0tp2+ttdVCQlMRM6VfCydKv0sTphlijriK","domain":"www.sbisec.co.jp","path":"/","expires":1756103837.464668,"size":130,"httpOnly":false,"secure":false,"session":false,"priority":"Medium","sameParty":false,"sourceScheme":"Secure","sourcePort":443},{"name":"AWSALBCORS","value":"DaC9ufoOOSYsszGVO/bA2F2sDPqqzFczEYVkCipe1H6Skk/7DkXwZX3AZ5/Z5NhuwYHYwPMT59xBIRvMrfLPQobCYT0tp2+ttdVCQlMRM6VfCydKv0sTphlijriK","domain":"www.sbisec.co.jp","path":"/","expires":1756103837.464712,"size":134,"httpOnly":false,"secure":true,"session":false,"sameSite":"None","priority":"Medium","sameParty":false,"sourceScheme":"Secure","sourcePort":443},{"name":"JSESSIONID","value":"smovzJ0EW2ehic1iJQV9vZsShHiCOjXOwyh7GJwL.prod-genesis-pl-prod-s04-008","domain":"www.sbisec.co.jp","path":"/","expires":-1,"size":79,"httpOnly":false,"secure":true,"session":true,"priority":"Medium","sameParty":false,"sourceScheme":"Secure","sourcePort":443},{"name":"2bac4997efa2631dc65b350295562df668b884ff768fc4fcdd0259f093cd2044","value":"a3eea4900275b3a879f99e2f7b59b9411fbffbdf231d48c7ed0f12bc3bc629e0&20250818153718","domain":".sbisec.co.jp","path":"/","expires":1787121438.541919,"size":143,"httpOnly":true,"secure":false,"session":false,"priority":"Medium","sameParty":false,"sourceScheme":"Secure","sourcePort":443},{"name":"JSESSIONID","value":"ySNIstJSWmrIEam1nVlWcGIYCkZO4zr3OE-aXRva.prod-genesis-pl-prod-s01-005","domain":"site1.sbisec.co.jp","path":"/","expires":-1,"size":79,"httpOnly":false,"secure":true,"session":true,"priority":"Medium","sameParty":false,"sourceScheme":"Secure","sourcePort":443},{"name":"login_info","value":"%7B%22data%22%3A%7B%22intermediaryProfile%22%3A%7B%22type%22%3A%22INCIDENTAL%22%2C%22code%22%3A%220508%22%2C%22name%22%3A%22%E4%BD%8F%E4%BF%A1SBI%E3%83%8D%E3%83%83%E3%83%88%E9%8A%80%E8%A1%8C%E6%A0%AA%E5%BC%8F%E4%BC%9A%E7%A4%BE%22%2C%22isShinkin%22%3Afalse%2C%22url%22%3A%22http%3A%2F%2Fwww.netbk.co.jp%2F%22%7D%2C%22aHash%22%3A%222bac4997efa2631dc65b350295562df668b884ff768fc4fcdd0259f093cd2044%22%2C%22hHash%22%3A%22e7945f230e0626f763715c0f2c07a1543bd0ac8527bedb8b7909c890d3e0f239%22%2C%22fromSite%22%3A%22https%3A%2F%2Fsite1.sbisec.co.jp%22%7D%7D","domain":".sbisec.co.jp","path":"/","expires":-1,"size":558,"httpOnly":false,"secure":false,"session":true,"priority":"Medium","sameParty":false,"sourceScheme":"Secure","sourcePort":443},{"name":"krt-lv-ss","value":"8c5fc670-e709-4e72-be75-fce0664fa193_1755499036954_1755499038614_3","domain":".sbisec.co.jp","path":"/","expires":1755509836,"size":75,"httpOnly":false,"secure":true,"session":false,"priority":"Medium","sameParty":false,"sourceScheme":"Secure","sourcePort":443},{"name":"AWSALB","value":"5wNUgvreKNE3m1F/gC9hm6myqcybiQRLCyxy+QhLOIstvAT/LoCBPglrmqHRI3WTNl2wMSM3sa/gzz6INe7Zshfgf/1brZGd5xvcXJxwiQWRDjKCKKyQoD7DOYgj","domain":"site1.sbisec.co.jp","path":"/","expires":1756103838.629572,"size":130,"httpOnly":false,"secure":false,"session":false,"priority":"Medium","sameParty":false,"sourceScheme":"Secure","sourcePort":443},{"name":"AWSALBCORS","value":"5wNUgvreKNE3m1F/gC9hm6myqcybiQRLCyxy+QhLOIstvAT/LoCBPglrmqHRI3WTNl2wMSM3sa/gzz6INe7Zshfgf/1brZGd5xvcXJxwiQWRDjKCKKyQoD7DOYgj","domain":"site1.sbisec.co.jp","path":"/","expires":1756103838.62961,"size":134,"httpOnly":false,"secure":true,"session":false,"sameSite":"None","priority":"Medium","sameParty":false,"sourceScheme":"Secure","sourcePort":443},{"name":"s_nr","value":"1755499038721-New","domain":".sbisec.co.jp","path":"/","expires":1756103838,"size":21,"httpOnly":false,"secure":false,"session":false,"priority":"Medium","sameParty":false,"sourceScheme":"Secure","sourcePort":443},{"name":"s_pv_pn","value":"%5B%5BB%5D%5D","domain":".sbisec.co.jp","path":"/","expires":-1,"size":20,"httpOnly":false,"secure":false,"session":true,"priority":"Medium","sameParty":false,"sourceScheme":"Secure","sourcePort":443},{"name":"s_pv_pn2","value":"main%3Awplethmr001tlst20","domain":".sbisec.co.jp","path":"/","expires":1755500838,"size":32,"httpOnly":false,"secure":false,"session":false,"priority":"Medium","sameParty":false,"sourceScheme":"Secure","sourcePort":443},{"name":"cto_bundle","value":"NL9dJ19OMmtWVmxrNVBZWUNLdkglMkY2Z1FrR3k0VHp5SjNqSCUyRmR1JTJGUHVzc1ElMkZldkk0NnhmViUyQkI5UTllNzl6blZ2bXpSJTJGbW15Q2p3ckk1bWRFVVU4OTNmWE1RS2tlZTNBRFJsajQlMkZuRkJWRXZrbnBidmFkJTJCWDZzR2YxZTZqN25abVAzVkZjZzRHVUNJN1h4ZkxYZFJNYSUyQnVBMlcwZkRhRmIlMkZTNGFxVEZ0SXcxNTczYyUzRA","domain":".sbisec.co.jp","path":"/","expires":1789663039,"size":276,"httpOnly":false,"secure":false,"session":false,"priority":"Medium","sameParty":false,"sourceScheme":"Secure","sourcePort":443},{"name":"ttcsid","value":"1755497381098::Dr66qTUDz2s8_ywMQEGj.1.1755499039389","domain":".sbisec.co.jp","path":"/","expires":1789195039,"size":57,"httpOnly":false,"secure":false,"session":false,"priority":"Medium","sameParty":false,"sourceScheme":"Secure","sourcePort":443},{"name":"_ga_2X743H1G05","value":"GS2.1.s1755497381$o1$g1$t1755499039$j60$l0$h0","domain":".sbisec.co.jp","path":"/","expires":1790059039.800747,"size":59,"httpOnly":false,"secure":false,"session":false,"priority":"Medium","sameParty":false,"sourceScheme":"Secure","sourcePort":443},{"name":"ttcsid_CRCHB8RC77UBSLKS3JEG","value":"1755497381098::tCyUOvCjYZ_nhdkTEqJA.1.1755499039838","domain":".sbisec.co.jp","path":"/","expires":1789195039,"size":78,"httpOnly":false,"secure":false,"session":false,"priority":"Medium","sameParty":false,"sourceScheme":"Secure","sourcePort":443},{"name":"ttcsid_CVM9U6RC77U8AG52F5QG","value":"1755497381098::PiXW6Qmu-8SMYFAxVtOZ.1.1755499039838","domain":".sbisec.co.jp","path":"/","expires":1789195039,"size":78,"httpOnly":false,"secure":false,"session":false,"priority":"Medium","sameParty":false,"sourceScheme":"Secure","sourcePort":443},{"name":"ttcsid_D1JMN7JC77U3JE50UBIG","value":"1755497381098::eKizaMk3_KwirIKKIiIe.1.1755499039838","domain":".sbisec.co.jp","path":"/","expires":1789195039,"size":78,"httpOnly":false,"secure":false,"session":false,"priority":"Medium","sameParty":false,"sourceScheme":"Secure","sourcePort":443},{"name":"cto_bundle","value":"v4tZ219CY3B3dWtET3glMkJLJTJGdmVpMTAlMkJCWnI4aUw0WlNqaVBGSFNVdVdsR1FsMkNvUyUyRnlBdnVuODBHN0tjdiUyQnd5bktxVndhR25tTXQ0OTdncXVIMVdJUE92MkZHdmhVVmhyRE9rMEtIRnBHNXZGVGZQRDNVdmlMJTJCdG5yRllDTWNQUnJpNnFGQnFseHJMSjZkU0pFR3l2dkc1aTZwJTJCblFoRUNjNERRRjdpUW1HY2E3SSUzRA","domain":".criteo.com","path":"/","expires":1789195040.009441,"size":268,"httpOnly":false,"secure":true,"session":false,"sameSite":"None","priority":"Medium","sameParty":false,"sourceScheme":"Secure","sourcePort":443,"partitionKey":{"sourceOrigin":"https://sbisec.co.jp","hasCrossSiteAncestor":true}},{"name":"audit_p","value":"1|pVrJxhgpDrNpmLxVrze/5e2UycrI7UyNmTArFbYAL6SRBYlpMMzXX+X4hDjJ5Yv0/UkB8oswWL6M1KxoLazIt+aleybw1oy9Ba0etFFpiE2Dp6V4mQigvkc6e2XP/ThCqvc5Z2Gc50jAuX09ZbVamBs+PYRysrw816qcCyXcJO7mQdVc7iIhNLYPAdWGRZ6V8p4Q5rMwDzg=","domain":".rubiconproject.com","path":"/","expires":1787035040.154888,"size":213,"httpOnly":false,"secure":true,"session":false,"sameSite":"None","priority":"Medium","sameParty":false,"sourceScheme":"Secure","sourcePort":443,"partitionKey":{"sourceOrigin":"https://sbisec.co.jp","hasCrossSiteAncestor":true}},{"name":"_uetsid","value":"ed6ad8507bf911f08f4b234db5d8491b|17edgde|2|fyk|0|2056","domain":".sbisec.co.jp","path":"/","expires":1755585441,"size":60,"httpOnly":false,"secure":false,"session":false,"priority":"Medium","sameParty":false,"sourceScheme":"Secure","sourcePort":443},{"name":"_uetvid","value":"ed6b2b907bf911f0afc73f216e295dbe|gwh9yy|1755499040324|6|1|bat.bing.com/p/conversions/c/k","domain":".sbisec.co.jp","path":"/","expires":1789195041,"size":95,"httpOnly":false,"secure":false,"session":false,"priority":"Medium","sameParty":false,"sourceScheme":"Secure","sourcePort":443},{"name":"_clsk","value":"1s9xplp%7C1755499041110%7C6%7C0%7Ck.clarity.ms%2Fcollect","domain":".sbisec.co.jp","path":"/","expires":1755585441,"size":61,"httpOnly":false,"secure":false,"session":false,"priority":"Medium","sameParty":false,"sourceScheme":"Secure","sourcePort":443},{"name":"__smn_fid","value":"_bGMxk8UZE9hvvgj_M1nYQiYhGcQvPiw3oszQIDX4dnDiK8U","domain":".sbisec.co.jp","path":"/","expires":1790059069.012658,"size":57,"httpOnly":false,"secure":false,"session":false,"priority":"Medium","sameParty":false,"sourceScheme":"Secure","sourcePort":443}]